fusion/__init__.py
fusion/model.py
py_gene_fusions-0.0.3.dist-info/LICENSE
py_gene_fusions-0.0.3.dist-info/METADATA
py_gene_fusions-0.0.3.dist-info/WHEEL
py_gene_fusions-0.0.3.dist-info/top_level.txt
py_gene_fusions-0.0.3.dist-info/RECORD
