Metadata-Version: 2.1
Name: py-gene-fusions
Version: 0.0.3
Summary: Package for structuring gene fusions
Home-page: https://github.com/cancervariants/py-gene-fusions
Author: Wagner Lab, Nationwide Childrens Hospital
License: MIT
Platform: UNKNOWN
Requires-Python: >=3.7
Requires-Dist: pydantic
Requires-Dist: gene-normalizer (>=0.1.14)
